Workbook

Sheet 01_Dashboard
A1: ENFLOW MANAGEMENT DASHBOARD
A2: Live management view. Metrics are calculated from working transaction sheets; complete transactions to activate the dashboard.
A4: Dashboard Date | B4: =TODAY() -> 46287 | D4: Factory | E4: ='99_Lists_Settings'!B25 -> Anekal 562106
A5: Month Start | B5: =EOMONTH(B4,-1)+1 -> 46266
A7: Orders Open | D7: Orders Due / Open | G7: Production Today | J7: Rejection Today
A8: =COUNTIFS('20_Orders'!K:K,"<>Closed",'20_Orders'!K:K,"<>Cancelled",'20_Orders'!A:A,"<>") -> 3 | D8: =COUNTIFS('20_Orders'!I:I,"<="&B4,'20_Orders'!K:K,"<>Closed",'20_Orders'!K:K,"<>Cancelled",'20_Orders'!A:A,"<>") -> 0 | G8: =SUMIFS('22_Production_Daily'!K:K,'22_Production_Daily'!B:B,B4) -> 0 | J8: =SUMIFS('22_Production_Daily'!L:L,'22_Production_Daily'!B:B,B4) -> 0
A11: Dispatch Today | D11: Wastage Today | G11: Open Complaints | J11: Low Stock Items
A12: =SUMIFS('27_Dispatch'!F:F,'27_Dispatch'!B:B,B4) -> 0 | D12: =SUMIFS('25_Wastage'!G:G,'25_Wastage'!B:B,B4) -> 0 | G12: =COUNTIFS('30_Complaints'!N:N,"<>Closed",'30_Complaints'!A:A,"<>") -> 3 | J12: =COUNTIF('23_Inventory_Ledger'!AA:AA,"REORDER") -> 0
A16: OPERATING KPIs | E16: DECISION SUPPORT / ALERTS
A17: Alert | B17: Meaning | C17: Source Target
A18: Orders due | B18: Open orders with required date <= dashboard date | C18: 0.95
A19: Material shortage | B19: Inventory current stock <= reorder point | C19: 0.02
A20: QC hold | B20: QC records with Pending/Fail result | C20: 0.02
A21: Production gap | B21: Planned qty > actual output | C21: 0.98
A22: Dispatch pending | B22: Approved orders not yet dispatched | C22: 0.95
A23: Complaint overdue | B23: Target closure date passed and status not Closed | C23: 0.95

Sheet 02_Daily_Control
A1: DAILY CONTROL CENTER
A2: One-page operational control for the manager/operations coordinator. Use transaction sheets for detailed entries.
A4: Control Area | B4: Purpose
A5: TODAY'S OPERATIONS | B5: Orders due today / overdue, planned production, actual output, rejection, dispatch, manpower.
A6: MORNING CHECK | B6: Material readiness, open orders, machine status, manpower and QC holds.
A7: END-OF-DAY CHECK | B7: Production posted, rejection/wastage posted, QC disposition complete, FG receipt posted, dispatch posted, attendance complete.
A8: DECISION FLAGS | B8: Low stock, delayed orders, production gap, repeated defects, breakdowns, pending approvals.
A11: Suggested daily sequence
A12: 1. Review Dashboard
A13: 2. Check due/open orders
A14: 3. Confirm material readiness
A15: 4. Review production plan
A16: 5. Record production + QC + wastage
A17: 6. Confirm FG availability
A18: 7. Prepare/approve dispatch
A19: 8. Close attendance and daily exceptions

Sheet 00_Start_Here
A1: ENFLOW BUSINESS OS — WORKING SYSTEM v1
A2: Working operational workbook built from Enflow Business OS Master Database v2. This is an implementation layer; unresolved values remain TO BE DEFINED.
A4: Item | B4: Definition
A5: Purpose | B5: Run day-to-day operations in one workbook and preserve a structure that can later be converted to an application.
A6: Source of truth | B6: Enflow_Business_OS_Master_Database_v2.docx — Version 2.0 dated 22-Sep-2026.
A7: Design rule | B7: Masters are entered once; transactions record what happened; dashboards calculate from transactions.
A8: Important | B8: Do not type directly into calculated stock/KPI cells. Use transaction sheets.
A9: Core flow | B9: Order → Planning → Material → Production → QC → Packing → Dispatch → Invoice/Collection
A10: Modules included | B10: Dashboard, Daily Control, Orders, Planning, Production, Inventory, QC, Wastage, Purchasing, Dispatch, Attendance, Maintenance, Complaints, Masters, BOM, Lists & KPI
A11: App-readiness | B11: Every transaction has an ID, date, status and responsible/approval fields where relevant.
A12: Unresolved data | B12: Use TO BE DEFINED rather than guessing. Complete the Setup/Lists sheet before live use.

Sheet 99_Lists_Settings
A1: LISTS & SETTINGS
A2: Controlled values for dropdowns. Expand these lists as the business finalizes rules.
A3: Status | B3: Order Status | C3: QC Result | D3: QC Disposition | E3: Attendance | F3: Transaction Type | G3: UOM | H3: Brand Type | I3: Business Model | J3: Priority | K3: Yes No | L3: Approval Status | M3: Work Type | N3: Payment Status
A4: Draft | B4: New | C4: Pass | D4: Accept | E4: Present | F4: Purchase Receipt | G4: PCS | H4: Own Brand | I4: Raw Material Supply | J4: High | K4: Yes | L4: Pending | M4: Without Cover | N4: Not Due
A5: Pending Approval | B5: Approved | C5: Fail | D5: Rework | E5: Absent | F5: Material Issue | G5: SET | H5: OEM | I5: Contract Manufacturing | J5: Medium | K5: No | L5: Approved | M5: With Cover | N5: Due
A6: Approved | B6: Planned | C6: Conditional | D6: Scrap | E6: Half Day | F6: Production Consumption | G6: ROLL | H6: Non-Branded | I6: Own-Brand Sales | J6: Low | L6: Rejected | N6: Partially Paid
A7: In Progress | B7: In Production | C7: Pending | D7: Return | E7: Leave | F7: Finished Goods Receipt | G7: KG | N7: Paid
A8: On Hold | B8: QC Pending | D8: Pending | E8: Weekly Off | F8: Transfer In | G8: MTR | N8: Overdue
A9: Completed | B9: Ready to Dispatch | E9: Holiday | F9: Transfer Out | G9: L
A10: Rejected | B10: Partially Dispatched | F10: Adjustment In | G10: DAY
A11: Cancelled | B11: Dispatched | F11: Adjustment Out | G11: HOUR
A12: Closed | B12: Closed | F12: Scrap
B13: Cancelled | F13: Rework
F14: Customer Return
F15: Vendor Return
A22: SYSTEM PARAMETERS
A23: Parameter | B23: Value | C23: Source / Note
A24: Company Name | B24: Enflow Sanitary | C24: Confirmed in source
A25: Factory Location | B25: Anekal 562106 | C25: Confirmed in source
A26: Production Target - Without Cover | B26: 700 | C26: pcs/day
A27: Production Target - With Cover | B27: 350 | C27: pcs/day
A28: Production Labour Rate | B28: 350 | C28: ₹/day/person
A29: Overtime Rate | B29: 100 | C29: Source says ₹100 extra when OT is worked; exact basis TO BE DEFINED
A30: Assembly Scrap Reference Min | B30: 0.01 | C30: Source estimate 1–2%
A31: Assembly Scrap Reference Max | B31: 0.02 | C31: Source estimate 1–2%
A32: On-Time Delivery Target | B32: 0.95 | C32: Source KPI
A33: Overall Rejection Target | B33: 0.02 | C33: Source KPI
A34: Inventory Accuracy Target | B34: 0.98 | C34: Source KPI
A35: Production Achievement Target | B35: 0.95 | C35: Source KPI
A36: First Pass Yield Target | B36: 0.98 | C36: Source KPI
A37: Machine Utilization Target | B37: 0.85 | C37: Source KPI
A38: On-Time Dispatch Target | B38: 0.95 | C38: Source KPI

Sheet 10_Master_Customers
A1: CUSTOMER MASTER
A2: One row per customer. Add customer-specific credit and freight rules here.
A4: Customer ID | B4: Customer Name | C4: Customer Type | D4: GSTIN | E4: Credit Terms Days | F4: Freight Rule | G4: Active | H4: Notes | I4: Created At | J4: Updated At

Sheet 11_Master_Vendors
A1: VENDOR MASTER
A2: Vendor-specific MOQ, lead time, payment terms and performance are stored here.
A4: Vendor ID | B4: Vendor Name | C4: Material Category | D4: MOQ | E4: Lead Time Days | F4: Payment Terms | G4: Approved Status | H4: Contact | I4: GST/Tax Details | J4: Notes

Sheet 12_Master_Products
A1: PRODUCT / SKU MASTER
A2: Normalize size, diameter, nut variant, brand and packaging instead of using one long product description.
A4: SKU | B4: Product Family | C4: Brand ID | D4: Brand Type | E4: Diameter mm | F4: Nut Variant | G4: Length Value | H4: Length UOM | I4: MRP | J4: Standard Weight | K4: Packaging ID | L4: Barcode | M4: Process Route | N4: Work Type | O4: Active | P4: Notes
A5: SKU-TBD | B5: PTMT connection pipe | C5: BR-ENFLOW | D5: Own Brand | E5: 13 | F5: Round | G5: 18 | H5: IN | I5: TO BE DEFINED | J5: TO BE DEFINED | K5: TO BE DEFINED | L5: TO BE DEFINED | M5: Assembly + Packing | N5: Without Cover | O5: Yes | P5: Starter row; final SKU structure TO BE DEFINED
A6: SKU-TBD | B6: PTMT connection pipe | C6: BR-ENFLOW | D6: Own Brand | E6: 13.5 | F6: Hex | G6: 24 | H6: IN | I6: TO BE DEFINED | J6: TO BE DEFINED | K6: TO BE DEFINED | L6: TO BE DEFINED | M6: Assembly + Packing | N6: With Cover | O6: Yes | P6: Example only; final SKU structure TO BE DEFINED

Sheet 13_Master_Materials
A1: MATERIAL MASTER
A2: Raw materials, components, packaging and semi-finished pipe are separate stockable items.
A4: Material ID | B4: Material Group | C4: Material Name | D4: Variant | E4: UOM | F4: MOQ | G4: Lead Time Days | H4: Reorder Point | I4: Safety Stock | J4: Preferred Vendor ID | K4: Active | L4: Notes
A5: MAT-13-RN | B5: 13 mm components | C5: Nut | D5: Round | E5: PCS | F5: TO BE DEFINED | G5: TO BE DEFINED | H5: TO BE DEFINED | I5: TO BE DEFINED | K5: Yes
A6: MAT-13-HN | B6: 13 mm components | C6: Nut | D6: Hex | E6: PCS | F6: TO BE DEFINED | G6: TO BE DEFINED | H6: TO BE DEFINED | I6: TO BE DEFINED | K6: Yes
A7: MAT-13-CAP | B7: 13 mm components | C7: Cap | D7: Common | E7: PCS | F7: TO BE DEFINED | G7: TO BE DEFINED | H7: TO BE DEFINED | I7: TO BE DEFINED | K7: Yes
A8: MAT-13-IN | B8: 13 mm components | C8: Inner | D8: Common | E8: PCS | F8: TO BE DEFINED | G8: TO BE DEFINED | H8: TO BE DEFINED | I8: TO BE DEFINED | K8: Yes
A9: MAT-13-KEY | B9: 13 mm components | C9: Key | D9: Common | E9: PCS | F9: TO BE DEFINED | G9: TO BE DEFINED | H9: TO BE DEFINED | I9: TO BE DEFINED | K9: Yes
A10: MAT-13-WASH | B10: 13 mm components | C10: Washer | D10: Common | E10: PCS | F10: TO BE DEFINED | G10: TO BE DEFINED | H10: TO BE DEFINED | I10: TO BE DEFINED | K10: Yes
A11: MAT-COV-3X21 | B11: Covers | C11: Cover | D11: 3×21 | E11: PCS | F11: TO BE DEFINED | G11: TO BE DEFINED | H11: TO BE DEFINED | I11: TO BE DEFINED | K11: Yes
A12: MAT-COV-3X26 | B12: Covers | C12: Cover | D12: 3×26 | E12: PCS | F12: TO BE DEFINED | G12: TO BE DEFINED | H12: TO BE DEFINED | I12: TO BE DEFINED | K12: Yes
A13: MAT-COV-8X10 | B13: Covers | C13: Cover | D13: 8×10 | E13: PCS | F13: TO BE DEFINED | G13: TO BE DEFINED | H13: TO BE DEFINED | I13: TO BE DEFINED | K13: Yes
A14: MAT-PIPE-13 | B14: Pipe | C14: Pipe | D14: 13 mm non-braider | E14: MTR | F14: TO BE DEFINED | G14: TO BE DEFINED | H14: TO BE DEFINED | I14: TO BE DEFINED | K14: Yes
A15: MAT-PIPE-135 | B15: Pipe | C15: Pipe | D15: 13.5 mm braider | E15: MTR | F15: TO BE DEFINED | G15: TO BE DEFINED | H15: TO BE DEFINED | I15: TO BE DEFINED | K15: Yes

Sheet 14_Master_Employees
A1: EMPLOYEE MASTER
A2: Employee records support attendance, production responsibility and labour costing.
A4: Employee ID | B4: Employee Name | C4: Role | D4: Department | E4: Joining Date | F4: Daily Labour Rate | G4: OT Rate | H4: Active | I4: Notes
A5: EMP-TBD | B5: Shivakumar | C5: Operations Coordinator | D5: Operations | E5: TO BE DEFINED | F5: 350 | G5: 100 | H5: Yes | I5: Attendance, production, QC entries, inventory transactions, dispatch preparation and daily reporting
A6: EMP-TBD | B6: Taha | C6: Manager | D6: Management | E6: TO BE DEFINED | F6: TO BE DEFINED | G6: TO BE DEFINED | H6: Yes | I6: Orders, priority, dispatch approval, QC approval, customer communication and planning

Sheet 15_Master_Machines
A1: MACHINE / WORK CENTRE MASTER
A2: Production planning requires actual machine/work-centre list and capacity; currently TO BE DEFINED.
A4: Machine ID | B4: Machine / Work Centre | C4: Process | D4: Capacity Per Day | E4: Capacity UOM | F4: Available Hours/Day | G4: Active | H4: Notes

Sheet 16_Master_Brands
A1: BRAND MASTER
A2: Source identifies Enflow and OEM/contract manufacturing.
A4: Brand ID | B4: Brand Name | C4: Brand Type | D4: Customer ID | E4: Active | F4: Notes
A5: BR-ENFLOW | B5: Enflow | C5: Own Brand | E5: Yes
A6: BR-OEM-TBD | B6: TO BE DEFINED | C6: OEM | D6: TO BE DEFINED | E6: Yes | F6: OEM brand list to be completed

Sheet 17_BOM
A1: BOM / PRODUCT COMPOSITION
A2: Use one row per parent-component relationship. Exact SKU-level BOM still needs completion.
A4: BOM ID | B4: Parent SKU | C4: Component ID | D4: Component Name | E4: Qty Per Finished Unit | F4: UOM | G4: Variant Rule | H4: Effective From | I4: Active | J4: Notes
A5: BOM-TBD | B5: SKU-TBD | C5: MAT-13-RN | D5: Nut Set - Round | E5: 1 | F5: SET | G5: 13 mm Round / 13.5 mm Round | H5: TO BE DEFINED | I5: Yes | J5: Source says 1 nut set per finished pipe
A6: BOM-TBD | B6: SKU-TBD | C6: MAT-COV-3X21 | D6: Cover | E6: 1 | F6: PCS | G6: Size-specific | H6: TO BE DEFINED | I6: Yes
A7: BOM-TBD | B7: SKU-TBD | C7: MAT-LABEL-TBD | D7: Label | E7: 2 | F7: PCS | G7: Size-specific | H7: TO BE DEFINED | I7: Yes | J7: Label master needs completion
A8: BOM-TBD | B8: SKU-TBD | C8: MAT-PIPE-TBD | D8: Pipe | E8: 1 | F8: PCS | G8: Size-specific | H8: TO BE DEFINED | I8: Yes | J8: Pipe component

Sheet 20_Orders
A1: SALES ORDERS
A2: Controlled order record. WhatsApp may communicate an order, but this sheet becomes the system record.
A4: Order ID | B4: Order Date | C4: Customer ID | D4: Customer PO No | E4: PO Date | F4: SKU | G4: Qty Ordered | H4: UOM | I4: Required Date | J4: Priority | K4: Status | L4: Approved By | M4: Approved At | N4: Notes

Sheet 21_Production_Plan
A1: PRODUCTION PLAN
A2: Converts approved orders into planned work. Due date drives priority.
A4: Plan ID | B4: Plan Date | C4: Order ID | D4: SKU | E4: Qty Planned | F4: UOM | G4: Work Type | H4: Machine ID | I4: Planned Start | J4: Planned End | K4: Manpower Planned | L4: Material Ready | M4: Status | N4: Planner | O4: Notes

Sheet 22_Production_Daily
A1: DAILY PRODUCTION
A2: Capture actual shop-floor execution. Required operational fields are based directly on the source process model.
A4: Job ID | B4: Production Date | C4: Plan ID | D4: Order ID | E4: SKU | F4: Process Step | G4: Machine ID | H4: Operator ID | I4: Work Type | J4: Input Qty | K4: Output Qty | L4: Rejection Qty | M4: Rework Qty | N4: Start Time | O4: End Time | P4: Downtime Min | Q4: QC Status | R4: Defect Code | S4: Remarks | T4: Entered By | U4: Approved By

Sheet 23_Inventory_Ledger
A1: INVENTORY TRANSACTION LEDGER
A2: Stock changes only through transactions. Do not directly edit stock balances.
A4: Txn ID | B4: Txn Date | C4: Txn Type | D4: Item ID | E4: Item Description | F4: UOM | G4: Qty In | H4: Qty Out | I4: Reference ID | J4: Order/Job ID | K4: Vendor/Customer ID | L4: QC Status | M4: Location | N4: Reason | O4: Entered By | P4: Approved By | Q4: Approval Status | S4: LIVE STOCK SUMMARY
S5: Item ID | T5: Item Description | U5: UOM | V5: Total In | W5: Total Out | X5: Current Stock | Y5: Reorder Point | Z5: Safety Stock | AA5: Status
S6: =IF('13_Master_Materials'!A5="","",'13_Master_Materials'!A5) -> MAT-13-RN | T6: =IF(S6="","",'13_Master_Materials'!C5) -> Nut | U6: =IF(S6="","",'13_Master_Materials'!E5) -> PCS | V6: =IF(S6="","",SUMIFS($G$5:$G$2000,$D$5:$D$2000,S6)) -> 0 | W6: =IF(S6="","",SUMIFS($H$5:$H$2000,$D$5:$D$2000,S6)) -> 0 | X6: =IF(S6="","",V6-W6) -> 0 | Y6: =IF(S6="","",'13_Master_Materials'!H5) -> TO BE DEFINED | Z6: =IF(S6="","",'13_Master_Materials'!I5) -> TO BE DEFINED | AA6: =IF(S6="","",IF(AND(ISNUMBER(Y6),X6<=Y6),"REORDER",IF(AND(ISNUMBER(Z6),X6<=Z6),"SAFETY STOCK","OK"))) -> OK
S7: =IF('13_Master_Materials'!A6="","",'13_Master_Materials'!A6) -> MAT-13-HN | T7: =IF(S7="","",'13_Master_Materials'!C6) -> Nut | U7: =IF(S7="","",'13_Master_Materials'!E6) -> PCS | V7: =IF(S7="","",SUMIFS($G$5:$G$2000,$D$5:$D$2000,S7)) -> 0 | W7: =IF(S7="","",SUMIFS($H$5:$H$2000,$D$5:$D$2000,S7)) -> 0 | X7: =IF(S7="","",V7-W7) -> 0 | Y7: =IF(S7="","",'13_Master_Materials'!H6) -> TO BE DEFINED | Z7: =IF(S7="","",'13_Master_Materials'!I6) -> TO BE DEFINED | AA7: =IF(S7="","",IF(AND(ISNUMBER(Y7),X7<=Y7),"REORDER",IF(AND(ISNUMBER(Z7),X7<=Z7),"SAFETY STOCK","OK"))) -> OK
S8: =IF('13_Master_Materials'!A7="","",'13_Master_Materials'!A7) -> MAT-13-CAP | T8: =IF(S8="","",'13_Master_Materials'!C7) -> Cap | U8: =IF(S8="","",'13_Master_Materials'!E7) -> PCS | V8: =IF(S8="","",SUMIFS($G$5:$G$2000,$D$5:$D$2000,S8)) -> 0 | W8: =IF(S8="","",SUMIFS($H$5:$H$2000,$D$5:$D$2000,S8)) -> 0 | X8: =IF(S8="","",V8-W8) -> 0 | Y8: =IF(S8="","",'13_Master_Materials'!H7) -> TO BE DEFINED | Z8: =IF(S8="","",'13_Master_Materials'!I7) -> TO BE DEFINED | AA8: =IF(S8="","",IF(AND(ISNUMBER(Y8),X8<=Y8),"REORDER",IF(AND(ISNUMBER(Z8),X8<=Z8),"SAFETY STOCK","OK"))) -> OK
S9: =IF('13_Master_Materials'!A8="","",'13_Master_Materials'!A8) -> MAT-13-IN | T9: =IF(S9="","",'13_Master_Materials'!C8) -> Inner | U9: =IF(S9="","",'13_Master_Materials'!E8) -> PCS | V9: =IF(S9="","",SUMIFS($G$5:$G$2000,$D$5:$D$2000,S9)) -> 0 | W9: =IF(S9="","",SUMIFS($H$5:$H$2000,$D$5:$D$2000,S9)) -> 0 | X9: =IF(S9="","",V9-W9) -> 0 | Y9: =IF(S9="","",'13_Master_Materials'!H8) -> TO BE DEFINED | Z9: =IF(S9="","",'13_Master_Materials'!I8) -> TO BE DEFINED | AA9: =IF(S9="","",IF(AND(ISNUMBER(Y9),X9<=Y9),"REORDER",IF(AND(ISNUMBER(Z9),X9<=Z9),"SAFETY STOCK","OK"))) -> OK
S10: =IF('13_Master_Materials'!A9="","",'13_Master_Materials'!A9) -> MAT-13-KEY | T10: =IF(S10="","",'13_Master_Materials'!C9) -> Key | U10: =IF(S10="","",'13_Master_Materials'!E9) -> PCS | V10: =IF(S10="","",SUMIFS($G$5:$G$2000,$D$5:$D$2000,S10)) -> 0 | W10: =IF(S10="","",SUMIFS($H$5:$H$2000,$D$5:$D$2000,S10)) -> 0 | X10: =IF(S10="","",V10-W10) -> 0 | Y10: =IF(S10="","",'13_Master_Materials'!H9) -> TO BE DEFINED | Z10: =IF(S10="","",'13_Master_Materials'!I9) -> TO BE DEFINED | AA10: =IF(S10="","",IF(AND(ISNUMBER(Y10),X10<=Y10),"REORDER",IF(AND(ISNUMBER(Z10),X10<=Z10),"SAFETY STOCK","OK"))) -> OK
S11: =IF('13_Master_Materials'!A10="","",'13_Master_Materials'!A10) -> MAT-13-WASH | T11: =IF(S11="","",'13_Master_Materials'!C10) -> Washer | U11: =IF(S11="","",'13_Master_Materials'!E10) -> PCS | V11: =IF(S11="","",SUMIFS($G$5:$G$2000,$D$5:$D$2000,S11)) -> 0 | W11: =IF(S11="","",SUMIFS($H$5:$H$2000,$D$5:$D$2000,S11)) -> 0 | X11: =IF(S11="","",V11-W11) -> 0 | Y11: =IF(S11="","",'13_Master_Materials'!H10) -> TO BE DEFINED | Z11: =IF(S11="","",'13_Master_Materials'!I10) -> TO BE DEFINED | AA11: =IF(S11="","",IF(AND(ISNUMBER(Y11),X11<=Y11),"REORDER",IF(AND(ISNUMBER(Z11),X11<=Z11),"SAFETY STOCK","OK"))) -> OK
S12: =IF('13_Master_Materials'!A11="","",'13_Master_Materials'!A11) -> MAT-COV-3X21 | T12: =IF(S12="","",'13_Master_Materials'!C11) -> Cover | U12: =IF(S12="","",'13_Master_Materials'!E11) -> PCS | V12: =IF(S12="","",SUMIFS($G$5:$G$2000,$D$5:$D$2000,S12)) -> 0 | W12: =IF(S12="","",SUMIFS($H$5:$H$2000,$D$5:$D$2000,S12)) -> 0 | X12: =IF(S12="","",V12-W12) -> 0 | Y12: =IF(S12="","",'13_Master_Materials'!H11) -> TO BE DEFINED | Z12: =IF(S12="","",'13_Master_Materials'!I11) -> TO BE DEFINED | AA12: =IF(S12="","",IF(AND(ISNUMBER(Y12),X12<=Y12),"REORDER",IF(AND(ISNUMBER(Z12),X12<=Z12),"SAFETY STOCK","OK"))) -> OK
S13: =IF('13_Master_Materials'!A12="","",'13_Master_Materials'!A12) -> MAT-COV-3X26 | T13: =IF(S13="","",'13_Master_Materials'!C12) -> Cover | U13: =IF(S13="","",'13_Master_Materials'!E12) -> PCS | V13: =IF(S13="","",SUMIFS($G$5:$G$2000,$D$5:$D$2000,S13)) -> 0 | W13: =IF(S13="","",SUMIFS($H$5:$H$2000,$D$5:$D$2000,S13)) -> 0 | X13: =IF(S13="","",V13-W13) -> 0 | Y13: =IF(S13="","",'13_Master_Materials'!H12) -> TO BE DEFINED | Z13: =IF(S13="","",'13_Master_Materials'!I12) -> TO BE DEFINED | AA13: =IF(S13="","",IF(AND(ISNUMBER(Y13),X13<=Y13),"REORDER",IF(AND(ISNUMBER(Z13),X13<=Z13),"SAFETY STOCK","OK"))) -> OK
S14: =IF('13_Master_Materials'!A13="","",'13_Master_Materials'!A13) -> MAT-COV-8X10 | T14: =IF(S14="","",'13_Master_Materials'!C13) -> Cover | U14: =IF(S14="","",'13_Master_Materials'!E13) -> PCS | V14: =IF(S14="","",SUMIFS($G$5:$G$2000,$D$5:$D$2000,S14)) -> 0 | W14: =IF(S14="","",SUMIFS($H$5:$H$2000,$D$5:$D$2000,S14)) -> 0 | X14: =IF(S14="","",V14-W14) -> 0 | Y14: =IF(S14="","",'13_Master_Materials'!H13) -> TO BE DEFINED | Z14: =IF(S14="","",'13_Master_Materials'!I13) -> TO BE DEFINED | AA14: =IF(S14="","",IF(AND(ISNUMBER(Y14),X14<=Y14),"REORDER",IF(AND(ISNUMBER(Z14),X14<=Z14),"SAFETY STOCK","OK"))) -> OK
S15: =IF('13_Master_Materials'!A14="","",'13_Master_Materials'!A14) -> MAT-PIPE-13 | T15: =IF(S15="","",'13_Master_Materials'!C14) -> Pipe | U15: =IF(S15="","",'13_Master_Materials'!E14) -> MTR | V15: =IF(S15="","",SUMIFS($G$5:$G$2000,$D$5:$D$2000,S15)) -> 0 | W15: =IF(S15="","",SUMIFS($H$5:$H$2000,$D$5:$D$2000,S15)) -> 0 | X15: =IF(S15="","",V15-W15) -> 0 | Y15: =IF(S15="","",'13_Master_Materials'!H14) -> TO BE DEFINED | Z15: =IF(S15="","",'13_Master_Materials'!I14) -> TO BE DEFINED | AA15: =IF(S15="","",IF(AND(ISNUMBER(Y15),X15<=Y15),"REORDER",IF(AND(ISNUMBER(Z15),X15<=Z15),"SAFETY STOCK","OK"))) -> OK
S16: =IF('13_Master_Materials'!A15="","",'13_Master_Materials'!A15) -> MAT-PIPE-135 | T16: =IF(S16="","",'13_Master_Materials'!C15) -> Pipe | U16: =IF(S16="","",'13_Master_Materials'!E15) -> MTR | V16: =IF(S16="","",SUMIFS($G$5:$G$2000,$D$5:$D$2000,S16)) -> 0 | W16: =IF(S16="","",SUMIFS($H$5:$H$2000,$D$5:$D$2000,S16)) -> 0 | X16: =IF(S16="","",V16-W16) -> 0 | Y16: =IF(S16="","",'13_Master_Materials'!H15) -> TO BE DEFINED | Z16: =IF(S16="","",'13_Master_Materials'!I15) -> TO BE DEFINED | AA16: =IF(S16="","",IF(AND(ISNUMBER(Y16),X16<=Y16),"REORDER",IF(AND(ISNUMBER(Z16),X16<=Z16),"SAFETY STOCK","OK"))) -> OK
S17: =IF('13_Master_Materials'!A16="","",'13_Master_Materials'!A16) | T17: =IF(S17="","",'13_Master_Materials'!C16) | U17: =IF(S17="","",'13_Master_Materials'!E16) | V17: =IF(S17="","",SUMIFS($G$5:$G$2000,$D$5:$D$2000,S17)) | W17: =IF(S17="","",SUMIFS($H$5:$H$2000,$D$5:$D$2000,S17)) | X17: =IF(S17="","",V17-W17) | Y17: =IF(S17="","",'13_Master_Materials'!H16) | Z17: =IF(S17="","",'13_Master_Materials'!I16) | AA17: =IF(S17="","",IF(AND(ISNUMBER(Y17),X17<=Y17),"REORDER",IF(AND(ISNUMBER(Z17),X17<=Z17),"SAFETY STOCK","OK")))
... S55: =IF('13_Master_Materials'!A54="","",'13_Master_Materials'!A54) | T55: =IF(S55="","",'13_Master_Materials'!C54) | U55: =IF(S55="","",'13_Master_Materials'!E54) | V55: =IF(S55="","",SUMIFS($G$5:$G$2000,$D$5:$D$2000,S55)) | W55: =IF(S55="","",SUMIFS($H$5:$H$2000,$D$5:$D$2000,S55)) | X55: =IF(S55="","",V55-W55) | Y55: =IF(S55="","",'13_Master_Materials'!H54) | Z55: =IF(S55="","",'13_Master_Materials'!I54) | AA55: =IF(S55="","",IF(AND(ISNUMBER(Y55),X55<=Y55),"REORDER",IF(AND(ISNUMBER(Z55),X55<=Z55),"SAFETY STOCK","OK")))

Sheet 24_QC
A1: QUALITY CONTROL
A2: Incoming, in-process, final and dispatch inspection records. Rejected FG must not become available stock until disposition.
A4: QC ID | B4: QC Date | C4: Stage | D4: Job/Order ID | E4: SKU/Item ID | F4: Supplier/Customer | G4: Lot/Batch | H4: Sample Qty | I4: Inspected Qty | J4: Accepted Qty | K4: Rejected Qty | L4: Result | M4: Defect Code | N4: Severity | O4: Cause | P4: Corrective Action | Q4: Disposition | R4: Approved By | S4: Approved At | T4: Remarks

Sheet 25_Wastage
A1: WASTAGE / SCRAP / REWORK
A2: Separate wastage data so material loss, production rejection and rework can be analyzed by cause.
A4: Wastage ID | B4: Date | C4: Job ID | D4: Order ID | E4: Item/SKU | F4: Process | G4: Qty | H4: UOM | I4: Wastage Type | J4: Defect/Reason | K4: Cause | L4: Disposition | M4: Estimated Value | N4: Responsible | O4: Approved By | P4: Remarks

Sheet 26_Purchasing
A1: PURCHASING
A2: Purchase request/order/receipt reference. Vendor-specific MOQ, lead time and payment terms come from Vendor Master.
A4: PO ID | B4: PO Date | C4: Vendor ID | D4: Material ID | E4: Qty Ordered | F4: UOM | G4: Rate | H4: Expected Date | I4: Qty Received | J4: Pending Qty | K4: QC Status | L4: PO Status | M4: Payment Status | N4: Approved By | O4: Notes
J5: =IF(OR(E5="",I5=""),"",E5-I5)
J6: =IF(OR(E6="",I6=""),"",E6-I6)
J7: =IF(OR(E7="",I7=""),"",E7-I7)
J8: =IF(OR(E8="",I8=""),"",E8-I8)
J9: =IF(OR(E9="",I9=""),"",E9-I9)
J10: =IF(OR(E10="",I10=""),"",E10-I10)
J11: =IF(OR(E11="",I11=""),"",E11-I11)
J12: =IF(OR(E12="",I12=""),"",E12-I12)
J13: =IF(OR(E13="",I13=""),"",E13-I13)
J14: =IF(OR(E14="",I14=""),"",E14-I14)
J15: =IF(OR(E15="",I15=""),"",E15-I15)
J16: =IF(OR(E16="",I16=""),"",E16-I16)
... J1004: =IF(OR(E1004="",I1004=""),"",E1004-I1004)

Sheet 27_Dispatch
A1: PACKING & DISPATCH
A2: Dispatch control linked to orders. Capture transporter/LR and dispatch approval.
A4: Dispatch ID | B4: Dispatch Date | C4: Order ID | D4: Customer ID | E4: SKU | F4: Qty | G4: UOM | H4: Packing Checked | I4: QC Checked | J4: Transporter | K4: LR/Reference | L4: Vehicle No | M4: Dispatch Status | N4: Approved By | O4: Invoice Ref | P4: Expected Delivery | Q4: Actual Delivery | R4: On Time | S4: Remarks
R5: =IF(OR(P5="",Q5=""),"",IF(Q5<=P5,"Yes","No"))
R6: =IF(OR(P6="",Q6=""),"",IF(Q6<=P6,"Yes","No"))
R7: =IF(OR(P7="",Q7=""),"",IF(Q7<=P7,"Yes","No"))
R8: =IF(OR(P8="",Q8=""),"",IF(Q8<=P8,"Yes","No"))
R9: =IF(OR(P9="",Q9=""),"",IF(Q9<=P9,"Yes","No"))
R10: =IF(OR(P10="",Q10=""),"",IF(Q10<=P10,"Yes","No"))
R11: =IF(OR(P11="",Q11=""),"",IF(Q11<=P11,"Yes","No"))
R12: =IF(OR(P12="",Q12=""),"",IF(Q12<=P12,"Yes","No"))
R13: =IF(OR(P13="",Q13=""),"",IF(Q13<=P13,"Yes","No"))
R14: =IF(OR(P14="",Q14=""),"",IF(Q14<=P14,"Yes","No"))
R15: =IF(OR(P15="",Q15=""),"",IF(Q15<=P15,"Yes","No"))
R16: =IF(OR(P16="",Q16=""),"",IF(Q16<=P16,"Yes","No"))
... R1004: =IF(OR(P1004="",Q1004=""),"",IF(Q1004<=P1004,"Yes","No"))

Sheet 28_Attendance
A1: ATTENDANCE & OVERTIME
A2: Daily attendance is the source for manpower and labour productivity.
A4: Attendance ID | B4: Date | C4: Employee ID | D4: Employee Name | E4: Role | F4: Status | G4: In Time | H4: Out Time | I4: OT Hours | J4: OT Approved | K4: OT Rate | L4: OT Amount | M4: Entered By | N4: Approved By | O4: Remarks
K5: =IF(J5="Yes",IFERROR(VLOOKUP(C5,'14_Master_Employees'!A:G,7,FALSE),""),"") | L5: =IF(OR(I5="",K5=""),"",I5*K5)
K6: =IF(J6="Yes",IFERROR(VLOOKUP(C6,'14_Master_Employees'!A:G,7,FALSE),""),"") | L6: =IF(OR(I6="",K6=""),"",I6*K6)
K7: =IF(J7="Yes",IFERROR(VLOOKUP(C7,'14_Master_Employees'!A:G,7,FALSE),""),"") | L7: =IF(OR(I7="",K7=""),"",I7*K7)
K8: =IF(J8="Yes",IFERROR(VLOOKUP(C8,'14_Master_Employees'!A:G,7,FALSE),""),"") | L8: =IF(OR(I8="",K8=""),"",I8*K8)
K9: =IF(J9="Yes",IFERROR(VLOOKUP(C9,'14_Master_Employees'!A:G,7,FALSE),""),"") | L9: =IF(OR(I9="",K9=""),"",I9*K9)
K10: =IF(J10="Yes",IFERROR(VLOOKUP(C10,'14_Master_Employees'!A:G,7,FALSE),""),"") | L10: =IF(OR(I10="",K10=""),"",I10*K10)
K11: =IF(J11="Yes",IFERROR(VLOOKUP(C11,'14_Master_Employees'!A:G,7,FALSE),""),"") | L11: =IF(OR(I11="",K11=""),"",I11*K11)
K12: =IF(J12="Yes",IFERROR(VLOOKUP(C12,'14_Master_Employees'!A:G,7,FALSE),""),"") | L12: =IF(OR(I12="",K12=""),"",I12*K12)
K13: =IF(J13="Yes",IFERROR(VLOOKUP(C13,'14_Master_Employees'!A:G,7,FALSE),""),"") | L13: =IF(OR(I13="",K13=""),"",I13*K13)
K14: =IF(J14="Yes",IFERROR(VLOOKUP(C14,'14_Master_Employees'!A:G,7,FALSE),""),"") | L14: =IF(OR(I14="",K14=""),"",I14*K14)
K15: =IF(J15="Yes",IFERROR(VLOOKUP(C15,'14_Master_Employees'!A:G,7,FALSE),""),"") | L15: =IF(OR(I15="",K15=""),"",I15*K15)
K16: =IF(J16="Yes",IFERROR(VLOOKUP(C16,'14_Master_Employees'!A:G,7,FALSE),""),"") | L16: =IF(OR(I16="",K16=""),"",I16*K16)
... K2004: =IF(J2004="Yes",IFERROR(VLOOKUP(C2004,'14_Master_Employees'!A:G,7,FALSE),""),"") | L2004: =IF(OR(I2004="",K2004=""),"",I2004*K2004)

Sheet 29_Maintenance
A1: MACHINE MAINTENANCE
A2: Capture downtime, breakdowns and preventive maintenance for machine utilization.
A4: Maintenance ID | B4: Date | C4: Machine ID | D4: Type | E4: Start Time | F4: End Time | G4: Downtime Min | H4: Issue/Work | I4: Root Cause | J4: Action | K4: Spare Used | L4: Cost | M4: Responsible | N4: Status | O4: Next PM Date | P4: Remarks

Sheet 30_Complaints
A1: CUSTOMER COMPLAINTS & RETURNS
A2: Track issue, RCA, corrective action and closure.
A4: Complaint ID | B4: Date | C4: Customer ID | D4: Order ID | E4: SKU | F4: Issue Category | G4: Severity | H4: Description | I4: Root Cause | J4: Corrective Action | K4: Responsible | L4: Target Closure | M4: Actual Closure | N4: Status | O4: Return Qty | P4: QC Disposition | Q4: Notes

Sheet 40_KPI_Definitions
A1: KPI DICTIONARY
A2: Definitions are taken from the source database. Dashboard formulas use transaction data where possible.
A4: KPI | B4: Definition | C4: Target | D4: Frequency | E4: Source Module | F4: Owner | G4: Status
A5: Sales Achievement | B5: Actual Sales ÷ Target Sales | C5: >=100% | D5: Monthly | E5: Finance / Sales | F5: Manager | G5: Defined
A6: Gross Profit Margin | B6: Gross Profit ÷ Sales | C6: >=20%* | D6: Monthly | E6: Finance | F6: Manager | G6: Target changeable based on actual costing
A7: On-Time Delivery | B7: Orders delivered on time ÷ total orders | C7: >=95% | D7: Monthly | E7: Orders / Dispatch | F7: Manager | G7: Defined
A8: Production Achievement | B8: Actual ÷ Planned ×100 | C8: >=95% | D8: Weekly | E8: Planning / Production | F8: Production | G8: Defined
A9: Overall Rejection | B9: Rejected pcs ÷ total production | C9: <=2% | D9: Weekly | E9: Production / QC | F9: QC | G9: Defined
A10: Customer Complaints | B10: Valid complaints/month | C10: <=2 | D10: Monthly | E10: Complaints | F10: Manager | G10: Defined
A11: Receivable Days | B11: Outstanding ÷ average daily sales | C11: Within agreed credit | D11: Monthly | E11: Finance | F11: Manager | G11: Defined
A12: Inventory Accuracy | B12: Physical vs system stock | C12: >=98% | D12: Monthly | E12: Inventory | F12: Store | G12: Defined
A13: Production Efficiency | B13: Actual output ÷ standard output ×100 | C13: >=90% | D13: Production | E13: Production | F13: Production | G13: Defined
A14: Rework Rate | B14: Rework qty ÷ production ×100 | C14: <=2% | D14: Production | E14: Production / QC | F14: QC | G14: Defined
A15: Machine Utilization | B15: Running hours ÷ available hours ×100 | C15: >=85% | D15: Production | E15: Production / Maintenance | F15: Production | G15: Defined
... A25: Machine Availability | B25: Available/running basis to be standardized | C25: >=95% | D25: Maintenance | E25: Maintenance | F25: Maintenance | G25: Needs definition
